.DS_Store
neuroboom/__init__.py
neuroboom/_version.py
neuroboom/aesthetics.py
neuroboom/connectivity.py
neuroboom/dendrogram.py
neuroboom/flywire_tools.py
neuroboom/morphoelec.py
neuroboom/morphoelectro.py
neuroboom/stats.py
neuroboom/utils.py
neuroboom/tests/__init__.py
neuroboom/tests/conftest.py
neuroboom/tests/test_examples.py
neuroboom-0.3.55.dist-info/AUTHORS.rst
neuroboom-0.3.55.dist-info/LICENSE
neuroboom-0.3.55.dist-info/METADATA
neuroboom-0.3.55.dist-info/WHEEL
neuroboom-0.3.55.dist-info/entry_points.txt
neuroboom-0.3.55.dist-info/top_level.txt
neuroboom-0.3.55.dist-info/RECORD
