Metadata-Version: 2.1
Name: neuroboom
Version: 0.3.55
Summary: A suite of python tools for visualisation and analysis of Connectomic data
Home-page: https://github.com/markuspleijzier/neuroboom
Author: Markus William Pleijzier
Author-email: mp824@cam.ac.uk
License: BSD (3-clause)
Platform: UNKNOWN
Classifier: Development Status :: 2 - Pre-Alpha
Classifier: Natural Language :: English
Classifier: Programming Language :: Python :: 3
Requires-Python: >=3.7
License-File: LICENSE
License-File: AUTHORS.rst
Requires-Dist: IPython
Requires-Dist: navis
Requires-Dist: matplotlib
Requires-Dist: numpy
Requires-Dist: networkx
Requires-Dist: plotly
Requires-Dist: pandas
Requires-Dist: python-catmaid
Requires-Dist: phate
Requires-Dist: seaborn
Requires-Dist: sklearn
Requires-Dist: scprep
Requires-Dist: scipy
Requires-Dist: tqdm
Requires-Dist: cloud-volume
Requires-Dist: fafbseg
